notify/__init__.py
notify/exceptions.py
notify/mail.py
notify/msgraph.py
notify/teams.py
notify/types.py
notify/utils.py
zyppnotify-1.0.1.dist-info/LICENSE
zyppnotify-1.0.1.dist-info/METADATA
zyppnotify-1.0.1.dist-info/WHEEL
zyppnotify-1.0.1.dist-info/top_level.txt
zyppnotify-1.0.1.dist-info/RECORD
