Metadata-Version: 2.1
Name: zyppnotify
Version: 1.0.1
Summary: Send users notifications through various platforms
Home-page: https://github.com/zypp-io/zyppnotify
Author: Zypp
Author-email: hello@zypp.io
Project-URL: Bug Tracker, https://github.com/zypp-io/zyppnotify/issues
Project-URL: Source, https://github.com/zypp-io/zyppnotify
Keywords: python,notifications,teams,e-mail
Classifier: Programming Language :: Python :: 3
Classifier: License :: OSI Approved :: MIT License
Classifier: Operating System :: OS Independent
Requires-Python: >=3.9
License-File: LICENSE
Requires-Dist: azure-identity>=1.16.1
Requires-Dist: Babel>=2.14.0
Requires-Dist: msgraph-core>=1.1.3
Requires-Dist: pandas>=2.2.2
Requires-Dist: tabulate>=0.8.10
Requires-Dist: msgraph-sdk~=1.5.4
Requires-Dist: pympler~=1.1
